{
	"info": {
		"_postman_id": "95cd259f-f2cd-4eee-8c1f-1754ee264460",
		"name": "REQRES api",
		"schema": "https://schema.getpostman.com/json/collection/v2.1.0/collection.json",
		"_exporter_id": "25253703",
		"_collection_link": "https://www.postman.com/docking-module-cosmologist-10894912/workspace/my-workspace/collection/25253703-95cd259f-f2cd-4eee-8c1f-1754ee264460?action=share&source=collection_link&creator=25253703"
	},
	"item": [
		{
			"name": "Users",
			"item": [
				{
					"name": "Get list users in page 1",
					"event": [
						{
							"listen": "test",
							"script": {
								"exec": [
									"\r",
									"pm.test(\"Response time is less than 2000ms\", function () {\r",
									"    pm.expect(pm.response.responseTime).to.be.below(2000);\r",
									"});\r",
									"pm.test(\"Status code is 200\", function () {\r",
									"    pm.response.to.have.status(200);\r",
									"});\r",
									""
								],
								"type": "text/javascript"
							}
						}
					],
					"request": {
						"auth": {
							"type": "noauth"
						},
						"method": "GET",
						"header": [],
						"url": {
							"raw": "{{REQURL}}/users?page=1",
							"host": [
								"{{REQURL}}"
							],
							"path": [
								"users"
							],
							"query": [
								{
									"key": "page",
									"value": "1"
								}
							]
						}
					},
					"response": []
				},
				{
					"name": "Get all users in page 2",
					"event": [
						{
							"listen": "test",
							"script": {
								"exec": [
									"pm.test('Status code is 200', function () {\r",
									"    pm.response.to.have.status(200);\r",
									"})\r",
									"\r",
									"pm.test(\"check the response body has first_name\", function () {\r",
									"    var jsonData = pm.response.json();\r",
									"    pm.expect(jsonData.data[0].first_name).to.eql(\"Michael\");\r",
									"});\r",
									"\r",
									""
								],
								"type": "text/javascript"
							}
						},
						{
							"listen": "prerequest",
							"script": {
								"exec": [
									"console.log(\"this is a log\")\r",
									"console.info(\"this i s an info\")\r",
									"console.warn(\"this is an worning\")\r",
									"console.error(\"this i an error\")"
								],
								"type": "text/javascript"
							}
						}
					],
					"request": {
						"method": "GET",
						"header": [],
						"url": {
							"raw": "{{REQURL}}/users?page=2",
							"host": [
								"{{REQURL}}"
							],
							"path": [
								"users"
							],
							"query": [
								{
									"key": "page",
									"value": "2"
								}
							]
						}
					},
					"response": []
				},
				{
					"name": "Get specific user more info",
					"event": [
						{
							"listen": "test",
							"script": {
								"exec": [
									"pm.test(\"Status code is 200\", function () {\r",
									"    pm.response.to.have.status(200);\r",
									"});\r",
									"pm.test(\"Response time is less than 2000ms\", function () {\r",
									"    pm.expect(pm.response.responseTime).to.be.below(2000);\r",
									"});"
								],
								"type": "text/javascript"
							}
						}
					],
					"request": {
						"method": "GET",
						"header": [
							{
								"key": "Content-Type",
								"value": "application/json",
								"type": "text"
							}
						],
						"url": {
							"raw": "{{REQURL}}/users/:id",
							"host": [
								"{{REQURL}}"
							],
							"path": [
								"users",
								":id"
							],
							"query": [
								{
									"key": "sortid",
									"value": "desc",
									"disabled": true
								}
							],
							"variable": [
								{
									"key": "id",
									"value": "2"
								}
							]
						}
					},
					"response": []
				},
				{
					"name": "Get specific user",
					"event": [
						{
							"listen": "test",
							"script": {
								"exec": [
									"pm.test(\"Status code is 200\", function () {\r",
									"    pm.response.to.have.status(200);\r",
									"});\r",
									"pm.test(\"Response time is less than 2000ms\", function () {\r",
									"    pm.expect(pm.response.responseTime).to.be.below(2000);\r",
									"});\r",
									""
								],
								"type": "text/javascript"
							}
						}
					],
					"request": {
						"method": "GET",
						"header": [
							{
								"key": "Content-Type",
								"value": "application/json",
								"type": "text"
							}
						],
						"url": {
							"raw": "{{REQURL}}/users/?id=3",
							"host": [
								"{{REQURL}}"
							],
							"path": [
								"users",
								""
							],
							"query": [
								{
									"key": "sortid",
									"value": "desc",
									"disabled": true
								},
								{
									"key": "id",
									"value": "3"
								}
							]
						}
					},
					"response": []
				},
				{
					"name": "update specific user",
					"event": [
						{
							"listen": "test",
							"script": {
								"exec": [
									"pm.test(\"Response time is less than 200ms\", function () {\r",
									"    pm.expect(pm.response.responseTime).to.be.below(200);\r",
									"});\r",
									"pm.test(\"Response time is less than 2000ms\", function () {\r",
									"    pm.expect(pm.response.responseTime).to.be.below(2000);\r",
									"});\r",
									""
								],
								"type": "text/javascript"
							}
						}
					],
					"request": {
						"method": "PUT",
						"header": [],
						"body": {
							"mode": "raw",
							"raw": "{\r\n    \"data\": {\r\n        \"id\": 3,\r\n        \"email\": \"emma.wong@reqres.in\",\r\n        \"first_name\": \"Emma Anna\",\r\n        \"last_name\": \"Wong\",\r\n        \"avatar\": \"https://reqres.in/img/faces/3-image.jpg\"\r\n    },\r\n    \"support\": {\r\n        \"url\": \"https://reqres.in/#support-heading\",\r\n        \"text\": \"To keep ReqRes free, contributions towards server costs are appreciated!\"\r\n    }\r\n}",
							"options": {
								"raw": {
									"language": "json"
								}
							}
						},
						"url": {
							"raw": "{{REQURL}}/users/{{ID}}",
							"host": [
								"{{REQURL}}"
							],
							"path": [
								"users",
								"{{ID}}"
							]
						}
					},
					"response": []
				},
				{
					"name": "Get user Not found",
					"event": [
						{
							"listen": "test",
							"script": {
								"exec": [
									"pm.test(\"Status code is 404\", function () {\r",
									"    pm.response.to.have.status(404);\r",
									"});\r",
									"pm.test(\"Response time is less than 2000ms\", function () {\r",
									"    pm.expect(pm.response.responseTime).to.be.below(2000);\r",
									"});"
								],
								"type": "text/javascript"
							}
						}
					],
					"request": {
						"method": "GET",
						"header": [],
						"url": {
							"raw": "{{REQURL}}/users/23",
							"host": [
								"{{REQURL}}"
							],
							"path": [
								"users",
								"23"
							]
						}
					},
					"response": []
				},
				{
					"name": "create new user",
					"event": [
						{
							"listen": "test",
							"script": {
								"exec": [
									"pm.test(\"Status code is 201\", function () {\r",
									"    pm.response.to.have.status(201);\r",
									"});\r",
									"pm.test(\"Response time is less than 2000ms\", function () {\r",
									"    pm.expect(pm.response.responseTime).to.be.below(2000);\r",
									"});\r",
									"\r",
									""
								],
								"type": "text/javascript"
							}
						}
					],
					"request": {
						"method": "POST",
						"header": [],
						"body": {
							"mode": "raw",
							"raw": "{\r\n    \"name\": \"morpheus\",\r\n    \"job\": \"leader\"\r\n}",
							"options": {
								"raw": {
									"language": "json"
								}
							}
						},
						"url": {
							"raw": "{{REQURL}}/users",
							"host": [
								"{{REQURL}}"
							],
							"path": [
								"users"
							]
						}
					},
					"response": []
				},
				{
					"name": "update new user",
					"event": [
						{
							"listen": "test",
							"script": {
								"exec": [
									"pm.test(\"Status code is 200\", function () {\r",
									"    pm.response.to.have.status(200);\r",
									"});\r",
									""
								],
								"type": "text/javascript"
							}
						}
					],
					"request": {
						"method": "PUT",
						"header": [],
						"body": {
							"mode": "raw",
							"raw": "{\r\n    \"name\": \"morpheus\",\r\n    \"job\": \"zion residenter\"\r\n\r\n    \r\n}",
							"options": {
								"raw": {
									"language": "json"
								}
							}
						},
						"url": {
							"raw": "{{REQURL}}/users/{{IDJ}}",
							"host": [
								"{{REQURL}}"
							],
							"path": [
								"users",
								"{{IDJ}}"
							]
						}
					},
					"response": []
				},
				{
					"name": "Delete new user",
					"event": [
						{
							"listen": "test",
							"script": {
								"exec": [
									"pm.test(\"Status code is 204\", function () {\r",
									"    pm.response.to.have.status(204);\r",
									"});\r",
									"pm.test(\"Status code name has string\", function () {\r",
									"    pm.response.to.have.status(\"No Content\");\r",
									"});"
								],
								"type": "text/javascript"
							}
						}
					],
					"request": {
						"method": "DELETE",
						"header": [],
						"url": {
							"raw": "{{REQURL}}/users/{{IDJ}}",
							"host": [
								"{{REQURL}}"
							],
							"path": [
								"users",
								"{{IDJ}}"
							]
						}
					},
					"response": []
				},
				{
					"name": "Delayed response",
					"request": {
						"method": "GET",
						"header": [],
						"url": {
							"raw": "{{REQURL}}/users?delay=3",
							"host": [
								"{{REQURL}}"
							],
							"path": [
								"users"
							],
							"query": [
								{
									"key": "delay",
									"value": "3"
								}
							]
						}
					},
					"response": []
				}
			]
		},
		{
			"name": "unkown",
			"item": [
				{
					"name": "Get all unkown",
					"event": [
						{
							"listen": "test",
							"script": {
								"exec": [
									"pm.test(\"Status code is 200\", function () {\r",
									"    pm.response.to.have.status(200);\r",
									"});\r",
									"pm.test(\"Response time is less than 2000ms\", function () {\r",
									"    pm.expect(pm.response.responseTime).to.be.below(2000);\r",
									"});"
								],
								"type": "text/javascript"
							}
						}
					],
					"request": {
						"method": "GET",
						"header": [],
						"url": {
							"raw": "{{REQURL}}/unkown",
							"host": [
								"{{REQURL}}"
							],
							"path": [
								"unkown"
							]
						}
					},
					"response": []
				},
				{
					"name": "Get Not found",
					"event": [
						{
							"listen": "test",
							"script": {
								"exec": [
									"pm.test(\"Status code is 404\", function () {\r",
									"    pm.response.to.have.status(404);\r",
									"});\r",
									"pm.test(\"Response time is less than 2000ms\", function () {\r",
									"    pm.expect(pm.response.responseTime).to.be.below(2000);\r",
									"});"
								],
								"type": "text/javascript"
							}
						}
					],
					"request": {
						"method": "GET",
						"header": [],
						"url": {
							"raw": "{{REQURL}}/unkown/23",
							"host": [
								"{{REQURL}}"
							],
							"path": [
								"unkown",
								"23"
							]
						}
					},
					"response": []
				}
			]
		},
		{
			"name": "Regestration",
			"item": [
				{
					"name": "SignUp succesfully",
					"event": [
						{
							"listen": "test",
							"script": {
								"exec": [
									"pm.test(\"Status code is 200\", function () {\r",
									"    pm.response.to.have.status(200);\r",
									"});\r",
									"\r",
									"\r",
									""
								],
								"type": "text/javascript"
							}
						}
					],
					"request": {
						"method": "POST",
						"header": [],
						"body": {
							"mode": "raw",
							"raw": "{\r\n    \"email\": \"{{email}}\",\r\n    \"password\": \"{{password}}\"\r\n}",
							"options": {
								"raw": {
									"language": "json"
								}
							}
						},
						"url": {
							"raw": "{{REQURL}}/{{endpoint1}}",
							"host": [
								"{{REQURL}}"
							],
							"path": [
								"{{endpoint1}}"
							]
						}
					},
					"response": []
				},
				{
					"name": "SignUp with data driven",
					"event": [
						{
							"listen": "test",
							"script": {
								"exec": [
									"pm.test(\"Status code is 201\", function () {\r",
									"    pm.response.to.have.status(201);\r",
									"});\r",
									"\r",
									"\r",
									""
								],
								"type": "text/javascript"
							}
						}
					],
					"request": {
						"method": "POST",
						"header": [],
						"body": {
							"mode": "raw",
							"raw": "{\r\n    \"email\": \"{{email}}\",\r\n    \"password\": \"{{password}}\"\r\n}",
							"options": {
								"raw": {
									"language": "json"
								}
							}
						},
						"url": {
							"raw": "{{REQURL}}/{{endpoint}}",
							"host": [
								"{{REQURL}}"
							],
							"path": [
								"{{endpoint}}"
							]
						}
					},
					"response": []
				},
				{
					"name": "unsuccessful SignUp",
					"event": [
						{
							"listen": "test",
							"script": {
								"exec": [
									"pm.test(\"Status code is 400\", function () {\r",
									"    pm.response.to.have.status(400);\r",
									"});\r",
									"pm.test(\"Status code name has string\", function () {\r",
									"    pm.response.to.have.status(\"Bad Request\");\r",
									"});"
								],
								"type": "text/javascript"
							}
						}
					],
					"request": {
						"method": "POST",
						"header": [],
						"body": {
							"mode": "raw",
							"raw": "{\r\n    \"email\": \"sydney@fife\"\r\n}",
							"options": {
								"raw": {
									"language": "json"
								}
							}
						},
						"url": {
							"raw": "{{REQURL}}/register",
							"host": [
								"{{REQURL}}"
							],
							"path": [
								"register"
							]
						}
					},
					"response": []
				},
				{
					"name": "login successfully",
					"event": [
						{
							"listen": "test",
							"script": {
								"exec": [
									"pm.test(\"Status code is 200\", function () {\r",
									"    pm.response.to.have.status(200);\r",
									"});\r",
									"var responseJson = pm.response.json();\r",
									"pm.environment.set(\"token\", responseJson.token);"
								],
								"type": "text/javascript"
							}
						}
					],
					"request": {
						"method": "POST",
						"header": [],
						"body": {
							"mode": "raw",
							"raw": "{\r\n    \"email\": \"eve.holt@reqres.in\",\r\n    \"password\": \"cityslicka\"\r\n}",
							"options": {
								"raw": {
									"language": "json"
								}
							}
						},
						"url": {
							"raw": "{{REQURL}}/login",
							"host": [
								"{{REQURL}}"
							],
							"path": [
								"login"
							]
						}
					},
					"response": []
				},
				{
					"name": "unsuccessful login",
					"event": [
						{
							"listen": "test",
							"script": {
								"exec": [
									"pm.test(\"Response time is less than 1000ms\", function () {\r",
									"    pm.expect(pm.response.responseTime).to.be.below(1000);\r",
									"});\r",
									"pm.test(\"Status code is 400\", function () {\r",
									"    pm.response.to.have.status(400);\r",
									"});"
								],
								"type": "text/javascript"
							}
						}
					],
					"request": {
						"method": "POST",
						"header": [],
						"body": {
							"mode": "raw",
							"raw": "{\r\n    \"email\": \"peter@klaven\"\r\n}",
							"options": {
								"raw": {
									"language": "json"
								}
							}
						},
						"url": {
							"raw": "{{REQURL}}/login",
							"host": [
								"{{REQURL}}"
							],
							"path": [
								"login"
							]
						}
					},
					"response": []
				}
			]
		}
	]
}